{
  "id": "4623296",
  "name": "博客",
  "font_family": "iconfont",
  "css_prefix_text": "icon-",
  "description": "",
  "glyphs": [
    {
      "icon_id": "10515220",
      "name": "折叠",
      "font_class": "zhedie",
      "unicode": "e647",
      "unicode_decimal": 58951
    },
    {
      "icon_id": "41109707",
      "name": "展开",
      "font_class": "zhedie-copy",
      "unicode": "e69d",
      "unicode_decimal": 59037
    },
    {
      "icon_id": "14668884",
      "name": "日志",
      "font_class": "rizhi",
      "unicode": "e613",
      "unicode_decimal": 58899
    },
    {
      "icon_id": "637764",
      "name": "个人",
      "font_class": "geren",
      "unicode": "e60f",
      "unicode_decimal": 58895
    },
    {
      "icon_id": "11808033",
      "name": "权限",
      "font_class": "quanxian",
      "unicode": "e69c",
      "unicode_decimal": 59036
    },
    {
      "icon_id": "1029198",
      "name": "信息",
      "font_class": "info-1-copy",
      "unicode": "e60a",
      "unicode_decimal": 58890
    },
    {
      "icon_id": "16290363",
      "name": "编辑",
      "font_class": "bianji",
      "unicode": "e624",
      "unicode_decimal": 58916
    },
    {
      "icon_id": "982337",
      "name": "主页",
      "font_class": "zhuye",
      "unicode": "e655",
      "unicode_decimal": 58965
    }
  ]
}
